[
{"title": "BlueDBM: an appliance for big data analytics", "year": "2015", "authors": ["Sang-Woo Jun", "Ming Liu", "Sungjin Lee", "Jamey Hicks", "John Ankcorn", "Myron King", "Shuotao Xu", " Arvind"]},
{"title": "Towards sustainable in-situ server systems in the big data era", "year": "2015", "authors": ["Chao Li", "Yang Hu", "Longjun Liu", "Juncheng Gu", "Mingcong Song", "Xiaoyao Liang", "Jingling Yuan", "Tao Li"]},
{"title": "DjiNN and Tonic: DNN as a service and its implications for future warehouse scale computers", "year": "2015", "authors": ["Johann Hauswald", "Yiping Kang", "Michael A. Laurenzano", "Quan Chen", "Cheng Li", "Trevor Mudge", "Ronald G. Dreslinski", "Jason Mars", "Lingjia Tang"]},
{"title": "A case for core-assisted bottleneck acceleration in GPUs: enabling flexible data compression with assist warps", "year": "2015", "authors": ["Nandita Vijaykumar", "Gennady Pekhimenko", "Adwait Jog", "Abhishek Bhowmick", "Rachata Ausavarungnirun", "Chita Das", "Mahmut Kandemir", "Todd C. Mowry", "Onur Mutlu"]},
{"title": "Harmonia: balancing compute and memory power in high-performance GPUs", "year": "2015", "authors": ["Indrani Paul", "Wei Huang", "Manish Arora", "Sudhakar Yalamanchili"]},
{"title": "Redundant memory mappings for fast access to large memories", "year": "2015", "authors": ["Vasileios Karakostas", "Jayneel Gandhi", "Furkan Ayar", "Adri\u00e1n Cristal", "Mark D. Hill", "Kathryn S. McKinley", "Mario Nemirovsky", "Michael M. Swift", "Osman \u00dcnsal"]},
{"title": "Page overlays: an enhanced virtual memory framework to enable fine-grained memory management", "year": "2015", "authors": ["Vivek Seshadri", "Gennady Pekhimenko", "Olatunji Ruwase", "Onur Mutlu", "Phillip B. Gibbons", "Michael A. Kozuch", "Todd C. Mowry", "Trishul Chilimbi"]},
{"title": "ShiDianNao: shifting vision processing closer to the sensor", "year": "2015", "authors": ["Zidong Du", "Robert Fasthuber", "Tianshi Chen", "Paolo Ienne", "Ling Li", "Tao Luo", "Xiaobing Feng", "Yunji Chen", "Olivier Temam"]},
{"title": "A scalable processing-in-memory accelerator for parallel graph processing", "year": "2015", "authors": ["Junwhan Ahn", "Sungpack Hong", "Sungjoo Yoo", "Onur Mutlu", "Kiyoung Choi"]},
{"title": "Efficient execution of memory access phases using dataflow specialization", "year": "2015", "authors": ["Chen-Han Ho", "Sung Jin Kim", "Karthikeyan Sankaralingam"]},
{"title": "Data reorganization in memory using 3D-stacked DRAM", "year": "2015", "authors": ["Berkin Akin", "Franz Franchetti", "James C. Hoe"]},
{"title": "Quantitative comparison of hardware transactional memory for Blue Gene/Q, zEnterprise EC12, Intel Core, and POWER8", "year": "2015", "authors": ["Takuya Nakaike", "Rei Odaira", "Matthew Gaudet", "Maged M. Michael", "Hisanobu Tomari"]},
{"title": "Profiling a warehouse-scale computer", "year": "2015", "authors": ["Svilen Kanev", "Juan Pablo Darago", "Kim Hazelwood", "Parthasarathy Ranganathan", "Tipp Moseley", "Gu-Yeon Wei", "David Brooks"]},
{"title": "Computer performance microscopy with S", "year": "2015", "authors": ["Xi Yang", "Stephen M. Blackburn", "Kathryn S. McKinley"]},
{"title": "Flexible software profiling of GPU architectures", "year": "2015", "authors": ["Mark Stephenson", "Siva Kumar Sastry Hari", "Yunsup Lee", "Eiman Ebrahimi", "Daniel R. Johnson", "David Nellans", "Mike O'Connor", "Stephen W. Keckler"]},
{"title": "BEAR: techniques for mitigating bandwidth bloat in gigascale DRAM caches", "year": "2015", "authors": ["Chiachen Chou", "Aamer Jaleel", "Moinuddin K. Qureshi"]},
{"title": "A fully associative, tagless DRAM cache", "year": "2015", "authors": ["Yongjun Lee", "Jongwon Kim", "Hakbeom Jang", "Hyunggyun Yang", "Jangwoo Kim", "Jinkyu Jeong", "Jae W. Lee"]},
{"title": "Multiple clone row DRAM: a low latency and area optimized DRAM", "year": "2015", "authors": ["Jungwhan Choi", "Wongyu Shin", "Jaemin Jang", "Jinwoong Suh", "Yongkee Kwon", "Youngsuk Moon", "Lee-Sup Kim"]},
{"title": "Flexible auto-refresh: enabling scalable and energy-efficient DRAM refresh reductions", "year": "2015", "authors": ["Ishwar Bhati", "Zeshan Chishti", "Shih-Lien Lu", "Bruce Jacob"]},
{"title": "Cost-effective speculative scheduling in high performance processors", "year": "2015", "authors": ["Arthur Perais", "Andr\u00e9 Seznec", "Pierre Michaud", "Andreas Sembrant", "Erik Hagersten"]},
{"title": "LaZy superscalar", "year": "2015", "authors": ["G\u00f6rkem A\u015f\u0131l\u0131o\u011flu", "Zhaoxiang Jin", "Murat K\u00f6ksal", "Omkar Javeri", "Soner \u00d6nder"]},
{"title": "The load slice core microarchitecture", "year": "2015", "authors": ["Trevor E. Carlson", "Wim Heirman", "Osman Allam", "Stefanos Kaxiras", "Lieven Eeckhout"]},
{"title": "Semantic locality and context-based prefetching using reinforcement learning", "year": "2015", "authors": ["Leeor Peled", "Shie Mannor", "Uri Weiser", "Yoav Etsion"]},
{"title": "Exploring the potential of heterogeneous von neumann/dataflow execution models", "year": "2015", "authors": ["Tony Nowatzki", "Vinay Gangadhar", "Karthikeyan Sankaralingam"]},
{"title": "SHRINK: reducing the ISA complexity via instruction recycling", "year": "2015", "authors": ["Bruno Cardoso Lopes", "Rafael Auler", "Luiz Ramos", "Edson Borin", "Rodolfo Azevedo"]},
{"title": "Branch vanguard: decomposing branch functionality into prediction and resolution instructions", "year": "2015", "authors": ["Daniel S. McFarlin", "Craig Zilles"]},
{"title": "PIM-enabled instructions: a low-overhead, locality-aware processing-in-memory architecture", "year": "2015", "authors": ["Junwhan Ahn", "Sungjoo Yoo", "Onur Mutlu", "Kiyoung Choi"]},
{"title": "SLIP: reducing wire energy in the memory hierarchy", "year": "2015", "authors": ["Subhasis Das", "Tor M. Aamodt", "William J. Dally"]},
{"title": "CloudMonatt: an architecture for security health monitoring and attestation of virtual machines in cloud computing", "year": "2015", "authors": ["Tianwei Zhang", "Ruby B. Lee"]},
{"title": "Reducing world switches in virtualized environment with flexible cross-world calls", "year": "2015", "authors": ["Wenhao Li", "Yubin Xia", "Haibo Chen", "Binyu Zang", "Haibing Guan"]},
{"title": "ArMOR: defending against memory consistency model mismatches in heterogeneous architectures", "year": "2015", "authors": ["Daniel Lustig", "Caroline Trippel", "Michael Pellauer", "Margaret Martonosi"]},
{"title": "C", "year": "2015", "authors": ["Cedomir Segulja", "Tarek S. Abdelrahman"]},
{"title": "MiSAR: minimalistic synchronization accelerator with resource overflow management", "year": "2015", "authors": ["Ching-Kai Liang", "Milos Prvulovic"]},
{"title": "Callback: efficient synchronization without invalidation with a directory just for spin-waiting", "year": "2015", "authors": ["Alberto Ros", "Stefanos Kaxiras"]},
{"title": "Thermal time shifting: leveraging phase change materials to reduce cooling costs in warehouse-scale computers", "year": "2015", "authors": ["Matt Skach", "Manish Arora", "Chang-Hong Hsu", "Qi Li", "Dean Tullsen", "Lingjia Tang", "Jason Mars"]},
{"title": "Heracles: improving resource efficiency at scale", "year": "2015", "authors": ["David Lo", "Liqun Cheng", "Rama Govindaraju", "Parthasarathy Ranganathan", "Christos Kozyrakis"]},
{"title": "HEB: deploying and managing hybrid energy buffers for improving datacenter efficiency and economy", "year": "2015", "authors": ["Longjun Liu", "Chao Li", "Hongbin Sun", "Yang Hu", "Juncheng Gu", "Tao Li", "Jingmin Xin", "Nanning Zheng"]},
{"title": "Architecting to achieve a billion requests per second throughput on a single key-value store server platform", "year": "2015", "authors": ["Sheng Li", "Hyeontaek Lim", "Victor W. Lee", "Jung Ho Ahn", "Anuj Kalia", "Michael Kaminsky", "David G. Andersen", "O. Seongil", "Sukhan Lee", "Pradeep Dubey"]},
{"title": "A variable warp size architecture", "year": "2015", "authors": ["Timothy G. Rogers", "Daniel R. Johnson", "Mike O'Connor", "Stephen W. Keckler"]},
{"title": "Warped-compression: enabling power efficient GPUs through register compression", "year": "2015", "authors": ["Sangpil Lee", "Keunsoo Kim", "Gunjae Koo", "Hyeran Jeon", "Won Woo Ro", "Murali Annavaram"]},
{"title": "CAWA: coordinated warp scheduling and cache prioritization for critical warp acceleration of GPGPU workloads", "year": "2015", "authors": ["Shin-Ying Lee", "Akhil Arunkumar", "Carole-Jean Wu"]},
{"title": "Dynamic thread block launch: a lightweight execution mechanism to support irregular applications on GPUs", "year": "2015", "authors": ["Jin Wang", "Norm Rubin", "Albert Sidelnik", "Sudhakar Yalamanchili"]},
{"title": "DynaSpAM: dynamic spatial architecture mapping using out of order instruction schedules", "year": "2015", "authors": ["Feng Liu", "Heejin Ahn", "Stephen R. Beard", "Taewook Oh", "David I. August"]},
{"title": "Rumba: an online quality management system for approximate computing", "year": "2015", "authors": ["Daya S. Khudia", "Babak Zamirai", "Mehrzad Samadi", "Scott Mahlke"]},
{"title": "Manycore network interfaces for in-memory rack-scale computing", "year": "2015", "authors": ["Alexandros Daglis", "Stanko Novakovi\u0107", "Edouard Bugnion", "Babak Falsafi", "Boris Grot"]},
{"title": "Unified address translation for memory-mapped SSDs with FlashMap", "year": "2015", "authors": ["Jian Huang", "Anirudh Badam", "Moinuddin K. Qureshi", "Karsten Schwan"]},
{"title": "FASE: finding amplitude-modulated side-channel emanations", "year": "2015", "authors": ["Robert Callan", "Alenka Zaji\u0107", "Milos Prvulovic"]},
{"title": "Probable cause: the deanonymizing effects of approximate DRAM", "year": "2015", "authors": ["Amir Rahmati", "Matthew Hicks", "Daniel E. Holcomb", "Kevin Fu"]},
{"title": "PrORAM: dynamic prefetcher for oblivious RAM", "year": "2015", "authors": ["Xiangyao Yu", "Syed Kamran Haider", "Ling Ren", "Christopher Fletcher", "Albert Kwon", "Marten van Dijk", "Srinivas Devadas"]},
{"title": "MBus: an ultra-low power interconnect bus for next generation nanopower systems", "year": "2015", "authors": ["Pat Pannuto", "Yoonmyung Lee", "Ye-Sheng Kuo", "ZhiYoong Foo", "Benjamin Kempke", "Gyouho Kim", "Ronald G. Dreslinski", "David Blaauw", "Prabal Dutta"]},
{"title": "Accelerating asynchronous programs through event sneak peek", "year": "2015", "authors": ["Gaurav Chadha", "Scott Mahlke", "Satish Narayanasamy"]},
{"title": "VIP: virtualizing IP chains on handheld platforms", "year": "2015", "authors": ["Nachiappan Chidambaram Nachiappan", "Haibo Zhang", "Jihyun Ryoo", "Niranjan Soundararajan", "Anand Sivasubramaniam", "Mahmut T. Kandemir", "Ravi Iyer", "Chita R. Das"]},
{"title": "FaultHound: value-locality-based soft-fault tolerance", "year": "2015", "authors": [" Nitin", "Irith Pomeranz", "T. N. Vijaykumar"]},
{"title": "COP: to compress and protect main memory", "year": "2015", "authors": ["David J. Palframan", "Nam Sung Kim", "Mikko H. Lipasti"]},
{"title": "Hi-fi playback: tolerating position errors in shift operations of racetrack memory", "year": "2015", "authors": ["Chao Zhang", "Guangyu Sun", "Xian Zhang", "Weiqi Zhang", "Weisheng Zhao", "Tao Wang", "Yun Liang", "Yongpan Liu", "Yu Wang", "Jiwu Shu"]},
{"title": "Stash: have your scratchpad and cache it too", "year": "2015", "authors": ["Rakesh Komuravelli", "Matthew D. Sinclair", "Johnathan Alsop", "Muhammad Huzaifa", "Maria Kotsifakou", "Prakalp Srivastava", "Sarita V. Adve", "Vikram S. Adve"]},
{"title": "Coherence protocol for transparent management of scratchpad memories in shared memory manycore architectures", "year": "2015", "authors": ["Lluc Alvarez", "Llu\u00eds Vilanova", "Miquel Moreto", "Marc Casas", "Marc Gonz\u00e0lez", "Xavier Martorell", "Nacho Navarro", "Eduard Ayguad\u00e9", "Mateo Valero"]},
{"title": "Fusion: design tradeoffs in coherent cache hierarchies for accelerators", "year": "2015", "authors": ["Snehasish Kumar", "Arrvindh Shriraman", "Naveen Vedula"]}
]