[
{"title": "Transforming data access through public visualization", "year": "2009", "authors": ["Fernanda B. Vi\u00e9gas", "Martin Wattenberg"]},
{"title": "A common database approach for OLTP and OLAP using an in-memory column database", "year": "2009", "authors": ["Hasso Plattner"]},
{"title": "Authenticated join processing in outsourced databases", "year": "2009", "authors": ["Yin Yang", "Dimitris Papadias", "Stavros Papadopoulos", "Panos Kalnis"]},
{"title": "Privacy integrated queries: an extensible platform for privacy-preserving data analysis", "year": "2009", "authors": ["Frank D. McSherry"]},
{"title": "Secure outsourced aggregation via one-way chains", "year": "2009", "authors": ["Suman Nath", "Haifeng Yu", "Haowen Chan"]},
{"title": "Dependency-aware reordering for parallelizing query optimization in multi-core CPUs", "year": "2009", "authors": ["Wook-Shin Han", "Jinsoo Lee"]},
{"title": "Query processing techniques for solid state drives", "year": "2009", "authors": ["Dimitris Tsirogiannis", "Stavros Harizopoulos", "Mehul A. Shah", "Janet L. Wiener", "Goetz Graefe"]},
{"title": "FlashLogging: exploiting flash devices for synchronous logging performance", "year": "2009", "authors": ["Shimin Chen"]},
{"title": "Efficiently incorporating user feedback into information extraction and integration programs", "year": "2009", "authors": ["Xiaoyong Chai", "Ba-Quy Vuong", "AnHai Doan", "Jeffrey F. Naughton"]},
{"title": "Uncertainty management in rule-based information extraction systems", "year": "2009", "authors": ["Eirinaios Michelakis", "Rajasekar Krishnamurthy", "Peter J. Haas", "Shivakumar Vaithyanathan"]},
{"title": "Skip-and-prune: cosine-based top-k query processing for efficient context-sensitive document retrieval", "year": "2009", "authors": ["Jong Wook Kim", "K. Sel\u00e7uk Candan"]},
{"title": "Attacks on privacy and deFinetti's theorem", "year": "2009", "authors": ["Daniel Kifer"]},
{"title": "Secure kNN computation on encrypted databases", "year": "2009", "authors": ["Wai Kit Wong", "David Wai-lok Cheung", "Ben Kao", "Nikos Mamoulis"]},
{"title": "Privacy preservation of aggregates in hidden databases: why and how?", "year": "2009", "authors": ["Arjun Dasgupta", "Nan Zhang", "Gautam Das", "Surajit Chaudhuri"]},
{"title": "A comparison of approaches to large-scale data analysis", "year": "2009", "authors": ["Andrew Pavlo", "Erik Paulson", "Alexander Rasin", "Daniel J. Abadi", "David J. DeWitt", "Samuel Madden", "Michael Stonebraker"]},
{"title": "Asynchronous view maintenance for VLSD databases", "year": "2009", "authors": ["Parag Agrawal", "Adam Silberstein", "Brian F. Cooper", "Utkarsh Srivastava", "Raghu Ramakrishnan"]},
{"title": "ZStream: a cost-based query processor for adaptively detecting composite events", "year": "2009", "authors": ["Yuan Mei", "Samuel Madden"]},
{"title": "Exploiting context analysis for combining multiple entity resolution systems", "year": "2009", "authors": ["Zhaoqi Chen", "Dmitri V. Kalashnikov", "Sharad Mehrotra"]},
{"title": "Entity resolution with iterative blocking", "year": "2009", "authors": ["Steven Euijong Whang", "David Menestrina", "Georgia Koutrika", "Martin Theobald", "Hector Garcia-Molina"]},
{"title": "A grammar-based entity representation framework for data cleaning", "year": "2009", "authors": ["Arvind Arasu", "Raghav Kaushik"]},
{"title": "Generating example data for dataflow programs", "year": "2009", "authors": ["Christopher Olston", "Shubham Chopra", "Utkarsh Srivastava"]},
{"title": "A framework for testing query transformation rules", "year": "2009", "authors": ["Hicham G. Elmongui", "Vivek Narasayya", "Ravishankar Ramamurthy"]},
{"title": "Cross-tier, label-based security enforcement for web applications", "year": "2009", "authors": ["Brian J. Corcoran", "Nikhil Swamy", "Michael Hicks"]},
{"title": "Dictionary-based order-preserving string compression for main memory column stores", "year": "2009", "authors": ["Carsten Binnig", "Stefan Hildenbrand", "Franz F\u00e4rber"]},
{"title": "Self-organizing tuple reconstruction in column-stores", "year": "2009", "authors": ["Stratos Idreos", "Martin L. Kersten", "Stefan Manegold"]},
{"title": "An architecture for recycling intermediates in a column-store", "year": "2009", "authors": ["Milena G. Ivanova", "Martin L. Kersten", "Niels J. Nes", "Romulo A.P. Gon\u00e7alves"]},
{"title": "Optimizing complex extraction programs over evolving text data", "year": "2009", "authors": ["Fei Chen", "Byron J. Gao", "AnHai Doan", "Jun Yang", "Raghu Ramakrishnan"]},
{"title": "Robust web extraction: an approach based on a probabilistic tree-edit model", "year": "2009", "authors": ["Nilesh Dalvi", "Philip Bohannon", "Fei Sha"]},
{"title": "Combining keyword search and forms for ad hoc querying of databases", "year": "2009", "authors": ["Eric Chu", "Akanksha Baid", "Xiaoyong Chai", "AnHai Doan", "Jeffrey Naughton"]},
{"title": "Ranking distributed probabilistic data", "year": "2009", "authors": ["Feifei Li", "Ke Yi", "Jeffrey Jestes"]},
{"title": "Top-k queries on uncertain data: on score distribution and typical answers", "year": "2009", "authors": ["Tingjian Ge", "Stan Zdonik", "Samuel Madden"]},
{"title": "Secondary-storage confidence computation for conjunctive queries with inequalities", "year": "2009", "authors": ["Dan Olteanu", "Jiewen Huang"]},
{"title": "Query simplification: graceful degradation for join-order optimization", "year": "2009", "authors": ["Thomas Neumann"]},
{"title": "Robust and efficient algorithms for rank join evaluation", "year": "2009", "authors": ["Jonathan Finger", "Neoklis Polyzotis"]},
{"title": "Incremental maintenance of length normalized indexes for approximate string matching", "year": "2009", "authors": ["Marios Hadjieleftheriou", "Nick Koudas", "Divesh Srivastava"]},
{"title": "E = MC^3: managing uncertain enterprise data in a cluster-computing environment", "year": "2009", "authors": ["Fei Xu", "Kevin Beyer", "Vuk Ercegovac", "Peter J. Haas", "Eugene J. Shekita"]},
{"title": "Indexing correlated probabilistic databases", "year": "2009", "authors": ["Bhargav Kanagal", "Amol Deshpande"]},
{"title": "Estimating the confidence of conditional functional dependencies", "year": "2009", "authors": ["Graham Cormode", "Lukasz Golab", "Korn Flip", "Andrew McGregor", "Divesh Srivastava", "Xi Zhang"]},
{"title": "Scalable skyline computation using object-based space partitioning", "year": "2009", "authors": ["Shiming Zhang", "Nikos Mamoulis", "David W. Cheung"]},
{"title": "Minimizing the communication cost for continuous skyline maintenance", "year": "2009", "authors": ["Zhenjie Zhang", "Reynold Cheng", "Dimitris Papadias", "Anthony K.H. Tung"]},
{"title": "Kernel-based skyline cardinality estimation", "year": "2009", "authors": ["Zhenjie Zhang", "Yin Yang", "Ruichu Cai", "Dimitris Papadias", "Anthony Tung"]},
{"title": "Why not?", "year": "2009", "authors": ["Adriane Chapman", "H. V. Jagadish"]},
{"title": "Query by output", "year": "2009", "authors": ["Quoc Trung Tran", "Chee-Yong Chan", "Srinivasan Parthasarathy"]},
{"title": "Detecting and resolving unsound workflow views for correct provenance analysis", "year": "2009", "authors": ["Peng Sun", "Ziyang Liu", "Susan B. Davidson", "Yi Chen"]},
{"title": "Quality and efficiency in high dimensional nearest neighbor search", "year": "2009", "authors": ["Yufei Tao", "Ke Yi", "Cheng Sheng", "Panos Kalnis"]},
{"title": "Continuous obstructed nearest neighbor queries in spatial databases", "year": "2009", "authors": ["Yunjun Gao", "Baihua Zheng"]},
{"title": "Monitoring path nearest neighbor in road networks", "year": "2009", "authors": ["Zaiben Chen", "Heng Tao Shen", "Xiaofang Zhou", "Jeffrey Xu Yu"]},
{"title": "Cost based plan selection for xpath", "year": "2009", "authors": ["Haris Georgiadis", "Minas Charalambides", "Vasilis Vassalos"]},
{"title": "ROX: run-time optimization of XQueries", "year": "2009", "authors": ["Riham Abdel Kader", "Peter Boncz", "Stefan Manegold", "Maurice van Keulen"]},
{"title": "Scalable join processing on very large RDF graphs", "year": "2009", "authors": ["Thomas Neumann", "Gerhard Weikum"]},
{"title": "Top-k generation of integrated schemas based on directed and weighted correspondences", "year": "2009", "authors": ["Ahmed Radwan", "Lucian Popa", "Ioana R. Stanoi", "Akmal Younis"]},
{"title": "Core schema mappings", "year": "2009", "authors": ["Giansalvatore Mecca", "Paolo Papotti", "Salvatore Raunich"]},
{"title": "A gauss function based approach for unbalanced ontology matching", "year": "2009", "authors": ["Qian Zhong", "Hanyu Li", "Juanzi Li", "Guotong Xie", "Jie Tang", "Lizhu Zhou", "Yue Pan"]},
{"title": "Keyword search in databases: the power of RDBMS", "year": "2009", "authors": ["Lu Qin", "Jeffrey Xu Yu", "Lijun Chang"]},
{"title": "Efficient type-ahead search on relational data: a TASTIER approach", "year": "2009", "authors": ["Guoliang Li", "Shengyue Ji", "Chen Li", "Jianhua Feng"]},
{"title": "Extending autocompletion to tolerate errors", "year": "2009", "authors": ["Surajit Chaudhuri", "Raghav Kaushik"]},
{"title": "DDE: from dewey to a fully dynamic XML labeling scheme", "year": "2009", "authors": ["Liang Xu", "Tok Wang Ling", "Huayu Wu", "Zhifeng Bao"]},
{"title": "Simplifying XML schema: effortless handling of nondeterministic regular expressions", "year": "2009", "authors": ["Geert Jan Bex", "Wouter Gelade", "Wim Martens", "Frank Neven"]},
{"title": "FlexRecs: expressing and combining flexible recommendations", "year": "2009", "authors": ["Georgia Koutrika", "Benjamin Bercovitz", "Hector Garcia-Molina"]},
{"title": "Efficient approximate entity extraction with edit distance constraints", "year": "2009", "authors": ["Wei Wang", "Chuan Xiao", "Xuemin Lin", "Chengqi Zhang"]},
{"title": "GAMPS: compressing multi sensor data by grouping and amplitude scaling", "year": "2009", "authors": ["Sorabh Gandhi", "Suman Nath", "Subhash Suri", "Jie Liu"]},
{"title": "Optimizing i/o-intensive transactions in highly interactive applications", "year": "2009", "authors": ["Mohamed A. Sharaf", "Panos K. Chrysanthis", "Alexandros Labrinidis", "Cristiana Amza"]},
{"title": "A revised r*-tree in comparison with related index structures", "year": "2009", "authors": ["Norbert Beckmann", "Bernhard Seeger"]},
{"title": "3-HOP: a high-compression indexing scheme for reachability query", "year": "2009", "authors": ["Ruoming Jin", "Yang Xiang", "Ning Ruan", "David Fuhry"]},
{"title": "Serial and parallel methods for i/o efficient suffix tree construction", "year": "2009", "authors": ["Amol Ghoting", "Konstantin Makarychev"]},
{"title": "Data warehouse technology by infobright", "year": "2009", "authors": ["Dominik \u015alezak", "Victoria Eastwood"]},
{"title": "Stream warehousing with DataDepot", "year": "2009", "authors": ["Lukasz Golab", "Theodore Johnson", "J. Spencer Seidel", "Vladislav Shkapenyuk"]},
{"title": "Peta-scale data warehousing at Yahoo!", "year": "2009", "authors": ["Mona Ahuja", "Cheng Che Chen", "Ravi Gottapu", "J\u00f6rg Hallmann", "Waqar Hasan", "Richard Johnson", "Maciek Kozyrczak", "Ramesh Pabbati", "Neeta Pandit", "Sreenivasulu Pokuri", "Krishna Uppala"]},
{"title": "Advances in flash memory SSD technology for enterprise database applications", "year": "2009", "authors": ["Sang-Won Lee", "Bongki Moon", "Chanik Park"]},
{"title": "Parallelizing extensible query optimizers", "year": "2009", "authors": ["Florian M. Waas", "Joseph M. Hellerstein"]},
{"title": "A data warehouse appliance for the mass market", "year": "2009", "authors": ["Ravi Krishnamurthy"]},
{"title": "A comparison of flexible schemas for software as a service", "year": "2009", "authors": ["Stefan Aulbach", "Dean Jacobs", "Alfons Kemper", "Michael Seibold"]},
{"title": "The design of the force.com multitenant internet application development platform", "year": "2009", "authors": ["Craig D. Weissman", "Steve Bobrowski"]},
{"title": "Filtered statistics", "year": "2009", "authors": ["Pawel Terlecki", "Hardik Bati", "Cesar Galindo-Legaria", "Peter Zabback"]},
{"title": "Partial join order optimization in the paraccel analytic database", "year": "2009", "authors": ["Yijou Chen", "Richard L. Cole", "William J. McKenna", "Sergei Perfilov", "Aman Sinha", "Eugene Szedenits, Jr."]},
{"title": "Dynamic plan generation for parameterized queries", "year": "2009", "authors": ["Ahmad Ghazal", "Dawit Seid", "Bhashyam Ramesh", "Alain Crolotte", "Manjula Koppuravuri", "Vinod G"]},
{"title": "Ordering, distinctness, aggregation, partitioning and DQP optimization in sybase ASE 15", "year": "2009", "authors": ["Mihnea Andrei", "Xun Cheng", "Sudipto Chowdhuri", "Curtis Johnson", "Edwin Seputis"]},
{"title": "Taming the storage dragon: the adventures of hoTMaN", "year": "2009", "authors": ["Shahram Ghandeharizadeh", "Andrew Goodney", "Chetan Sharma", "Chris Bissell", "Felipe Carino", "Naveen Nannapaneni", "Alex Wergeles", "Aber Whitcomb"]},
{"title": "Compensation-aware data types in RDBMS", "year": "2009", "authors": ["Aravind Yalamanchi", "Dieter Gawlick"]},
{"title": "Access control in the aqualogic data services platform", "year": "2009", "authors": ["Vinayak Borkar", "Michael Carey", "Daniel Engovatov", "Dmitry Lychagin", "Panagiotis Reveliotis", "Joshua Spiegel", "Sachin Thatte", "Till Westmann"]},
{"title": "Building community-centric information exploration applications on social content sites", "year": "2009", "authors": ["Sihem Amer-Yahia", "Jian Huang", "Cong Yu"]},
{"title": "QoX-driven ETL design: reducing the cost of ETL consulting engagements", "year": "2009", "authors": ["Alkis Simitsis", "Kevin Wilkinson", "Malu Castellanos", "Umeshwar Dayal"]},
{"title": "Query optimizers: time to rethink the contract?", "year": "2009", "authors": ["Surajit Chaudhuri"]},
{"title": "Design for interaction", "year": "2009", "authors": ["Daniel Tunkelang"]},
{"title": "Voyagers and voyeurs: supporting social data analysis", "year": "2009", "authors": ["Jeffrey Heer"]},
{"title": "Augmented social cognition: using social web technology to enhance the ability of groups to remember, think, and reason", "year": "2009", "authors": ["Ed H. Chi"]},
{"title": "Storage class memory: technology, systems and applications", "year": "2009", "authors": ["Richard F. Freitas"]},
{"title": "Distributed data-parallel computing using a high-level programming language", "year": "2009", "authors": ["Michael Isard", "Yuan Yu"]}
]